{
  "conceptScheme": {
    "propertyOrder": [
      {
        "path": "http://www.w3.org/1999/02/22-rdf-syntax-ns#type",
        "order": 0
      },
      {
        "path": "http://www.w3.org/2004/02/skos/core#prefLabel",
        "order": 1,
        "simpleView": true
      },
      {
        "path": "http://www.w3.org/2004/02/skos/core#definition",
        "order": 2,
        "simpleView": true
      },
      {
        "path": "http://www.w3.org/2004/02/skos/core#historyNote",
        "order": 3,
        "simpleView": true
      },
      {
        "path": "http://purl.org/linked-data/registry#status",
        "order": 4,
        "simpleView": true
      },
      {
        "path": "http://www.w3.org/2002/07/owl#versionIRI",
        "order": 5,
        "simpleView": true
      },
      {
        "path": "https://schema.org/creator",
        "order": 6,
        "simpleView": true
      },
      {
        "path": "https://schema.org/publisher",
        "order": 7,
        "simpleView": true
      },
      {
        "path": "https://schema.org/dateCreated",
        "order": 8,
        "simpleView": true
      },
      {
        "path": "https://schema.org/dateModified",
        "order": 9,
        "simpleView": true
      },
      {
        "path": "https://schema.org/keywords",
        "order": 10,
        "simpleView": true
      },
      {
        "path": "https://schema.org/version",
        "order": 11,
        "simpleView": true
      },
      {
        "path": "http://www.w3.org/ns/prov#qualifiedAttribution",
        "order": 12,
        "propertyOrder": [
          {
            "path": "http://www.w3.org/ns/prov#agent",
            "order": 0,
            "minCount": 1,
            "maxCount": 1,
            "class": "http://www.w3.org/ns/prov#Agent"
          },
          {
            "path": "http://www.w3.org/ns/prov#hadRole",
            "order": 1,
            "minCount": 1,
            "maxCount": 1,
            "allowedValues": [
              "https://linked.data.gov.au/def/data-roles/custodian",
              "https://linked.data.gov.au/def/data-roles/pointOfContact"
            ]
          }
        ]
      },
      {
        "path": "http://purl.org/dc/terms/provenance",
        "order": 13,
        "simpleView": true
      },
      {
        "path": "http://purl.org/dc/terms/title",
        "order": 14,
        "simpleView": true
      },
      {
        "path": "http://www.w3.org/2004/02/skos/core#scopeNote",
        "order": 15,
        "simpleView": true
      },
      {
        "path": "http://purl.org/vocab/vann/usageNote",
        "order": 16,
        "simpleView": true
      },
      {
        "path": "https://schema.org/citation",
        "order": 17,
        "simpleView": true
      },
      {
        "path": "https://schema.org/license",
        "order": 18,
        "simpleView": true
      }
    ]
  },
  "concept": {
    "propertyOrder": [
      {
        "path": "http://www.w3.org/1999/02/22-rdf-syntax-ns#type",
        "order": 0
      },
      {
        "path": "http://www.w3.org/2004/02/skos/core#definition",
        "order": 1,
        "simpleView": true
      },
      {
        "path": "http://www.w3.org/2004/02/skos/core#narrower",
        "order": 2
      },
      {
        "path": "http://www.w3.org/2004/02/skos/core#broader",
        "order": 3
      },
      {
        "path": "http://www.w3.org/2004/02/skos/core#related",
        "order": 4,
        "simpleView": true
      },
      {
        "path": "http://www.w3.org/2004/02/skos/core#inScheme",
        "order": 5
      },
      {
        "path": "http://purl.org/dc/terms/identifier",
        "order": 6,
        "simpleView": true
      },
      {
        "path": "http://www.w3.org/2004/02/skos/core#topConceptOf",
        "order": 7
      },
      {
        "path": "http://www.w3.org/2004/02/skos/core#prefLabel",
        "order": 8,
        "simpleView": true
      },
      {
        "path": "http://www.w3.org/2004/02/skos/core#altLabel",
        "order": 9,
        "simpleView": true
      },
      {
        "path": "http://www.w3.org/2004/02/skos/core#notation",
        "order": 10,
        "simpleView": true
      },
      {
        "path": "http://www.w3.org/2004/02/skos/core#scopeNote",
        "order": 11,
        "simpleView": true
      },
      {
        "path": "http://www.w3.org/2004/02/skos/core#historyNote",
        "order": 12,
        "simpleView": true
      },
      {
        "path": "http://www.w3.org/2004/02/skos/core#example",
        "order": 13,
        "simpleView": true
      },
      {
        "path": "http://purl.org/vocab/vann/usageNote",
        "order": 14,
        "simpleView": true
      },
      {
        "path": "http://purl.org/dc/terms/provenance",
        "order": 15,
        "simpleView": true
      },
      {
        "path": "http://purl.org/linked-data/registry#status",
        "order": 16,
        "simpleView": true
      }
    ]
  },
  "catalog": {
    "propertyOrder": []
  },
  "list": {
    "propertyOrder": [
      {
        "path": "prefLabel",
        "order": 0
      },
      {
        "path": "iri",
        "order": 1
      },
      {
        "path": "broader",
        "order": 2
      }
    ]
  },
  "nestedOrder": {
    "http://www.w3.org/ns/prov#qualifiedAttribution": [
      {
        "path": "http://www.w3.org/ns/prov#agent",
        "order": 0
      },
      {
        "path": "http://www.w3.org/ns/prov#hadRole",
        "order": 1
      }
    ],
    "https://schema.org/temporalCoverage": [
      {
        "path": "https://schema.org/startTime",
        "order": 0
      },
      {
        "path": "https://schema.org/endTime",
        "order": 1
      }
    ]
  }
}